{
  "numRecordings": "4",
  "numSpecies": "1",
  "page": 1,
  "numPages": 1,
  "recordings": [
    {
      "id": "346744",
      "gen": "Corythaixoides",
      "sp": "concolor",
      "ssp": "",
      "en": "Grey Go-away-bird",
      "rec": "Peter Boesman",
      "cnt": "Namibia",
      "loc": "Omaruru area west",
      "lat": "-21.447504",
      "lng": "15.887621",
      "alt": "",
      "type": "call",
      "url": "//xeno-canto.org/346744",
      "file": "https://xeno-canto.org/346744/download",
      "file-name": "XC346744-LS102466 Go away bird calls A.mp3",
      "sono": {
        "small": "//xeno-canto.org/sounds/uploaded/OOECIWCSWV/ffts/XC346744-small.png",
        "med": "//xeno-canto.org/sounds/uploaded/OOECIWCSWV/ffts/XC346744-med.png",
        "large": "//xeno-canto.org/sounds/uploaded/OOECIWCSWV/ffts/XC346744-large.png",
        "full": "//xeno-canto.org/sounds/uploaded/OOECIWCSWV/ffts/XC346744-full.png"
      },
      "lic": "//creativecommons.org/licenses/by-nc-nd/4.0/",
      "q": "A",
      "length": "0:07",
      "time": "7:30",
      "date": "2016-11-11",
      "uploaded": "2016-12-19",
      "also": [
        ""
      ],
      "rmk": "",
      "bird-seen": "unknown",
      "playback-used": "unknown"
    },
    {
      "id": "346746",
      "gen": "Corythaixoides",
      "sp": "concolor",
      "ssp": "",
      "en": "Grey Go-away-bird",
      "rec": "Peter Boesman",
      "cnt": "Namibia",
      "loc": "Omaruru area west",
      "lat": "-21.447504",
      "lng": "15.887621",
      "alt": "",
      "type": "call",
      "url": "//xeno-canto.org/346746",
      "file": "https://xeno-canto.org/346746/download",
      "file-name": "XC346746-LS102478 Go away bird calls B.mp3",
      "sono": {
        "small": "//xeno-canto.org/sounds/uploaded/OOECIWCSWV/ffts/XC346746-small.png",
        "med": "//xeno-canto.org/sounds/uploaded/OOECIWCSWV/ffts/XC346746-med.png",
        "large": "//xeno-canto.org/sounds/uploaded/OOECIWCSWV/ffts/XC346746-large.png",
        "full": "//xeno-canto.org/sounds/uploaded/OOECIWCSWV/ffts/XC346746-full.png"
      },
      "lic": "//creativecommons.org/licenses/by-nc-nd/4.0/",
      "q": "B",
      "length": "0:08",
      "time": "8:00",
      "date": "2016-11-11",
      "uploaded": "2016-12-19",
      "also": [
        ""
      ],
      "rmk": "",
      "bird-seen": "unknown",
      "playback-used": "unknown"
    },
    {
      "id": "346745",
      "gen": "Corythaixoides",
      "sp": "concolor",
      "ssp": "",
      "en": "Grey Go-away-bird",
      "rec": "Peter Boesman",
      "cnt": "Namibia",
      "loc": "Omaruru area west",
      "lat": "-21.447504",
      "lng": "15.887621",
      "alt": "",
      "type": "call",
      "url": "//xeno-canto.org/346745",
      "file": "https://xeno-canto.org/346745/download",
      "file-name": "XC346745-LS102429 Go away bird calls B.mp3",
      "sono": {
        "small": "//xeno-canto.org/sounds/uploaded/OOECIWCSWV/ffts/XC346745-small.png",
        "med": "//xeno-canto.org/sounds/uploaded/OOECIWCSWV/ffts/XC346745-med.png",
        "large": "//xeno-canto.org/sounds/uploaded/OOECIWCSWV/ffts/XC346745-large.png",
        "full": "//xeno-canto.org/sounds/uploaded/OOECIWCSWV/ffts/XC346745-full.png"
      },
      "lic": "//creativecommons.org/licenses/by-nc-nd/4.0/",
      "q": "B",
      "length": "0:22",
      "time": "17:00",
      "date": "2016-11-10",
      "uploaded": "2016-12-19",
      "also": [
        ""
      ],
      "rmk": "",
      "bird-seen": "unknown",
      "playback-used": "unknown"
    },
    {
      "id": "58644",
      "gen": "Corythaixoides",
      "sp": "concolor",
      "ssp": "pallidiceps",
      "en": "Grey Go-away-bird",
      "rec": "Charles Hesse",
      "cnt": "Namibia",
      "loc": "Erongo, Namibia",
      "lat": "-21.459",
      "lng": "15.878",
      "alt": "1200",
      "type": "call",
      "url": "//xeno-canto.org/58644",
      "file": "https://xeno-canto.org/58644/download",
      "file-name": "174GRGAB0911141052NAER2.mp3",
      "sono": {
        "small": "//xeno-canto.org/sounds/uploaded/FMQSRXIRTH/ffts/XC58644-small.png",
        "med": "//xeno-canto.org/sounds/uploaded/FMQSRXIRTH/ffts/XC58644-med.png",
        "large": "//xeno-canto.org/sounds/uploaded/FMQSRXIRTH/ffts/XC58644-large.png",
        "full": "//xeno-canto.org/sounds/uploaded/FMQSRXIRTH/ffts/XC58644-full.png"
      },
      "lic": "//creativecommons.org/licenses/by-nc-nd/2.5/",
      "q": "B",
      "length": "0:20",
      "time": "10:52",
      "date": "2009-11-14",
      "uploaded": "2010-07-25",
      "also": [
        ""
      ],
      "rmk": "link:http://www.tropicalbirding.com",
      "bird-seen": "unknown",
      "playback-used": "unknown"
    }
  ]
}